ratelimitcli/__init__.py
ratelimitcli/__main__.py
ratelimitcli/billing/__init__.py
ratelimitcli/billing/billing.py
ratelimitcli/client/__init__.py
ratelimitcli/client/client.py
ratelimitcli/client/decorator.py
ratelimitcli/conf/.env
ratelimitcli/conf/__init__.py
ratelimitcli/config/__init__.py
ratelimitcli/config/config_file_serde.py
ratelimitcli/config/configure.py
ratelimitcli/config/middlewear.py
ratelimitcli/limits/__init__.py
ratelimitcli/limits/cli.thrift
ratelimitcli/limits/limits.py
ratelimitcli/limits/read_write.py
ratelimitcli/main.py
ratelimitcli-0.1.1.dist-info/entry_points.txt
ratelimitcli-0.1.1.dist-info/LICENSE
ratelimitcli-0.1.1.dist-info/WHEEL
ratelimitcli-0.1.1.dist-info/METADATA
ratelimitcli-0.1.1.dist-info/RECORD
