Metadata-Version: 2.1
Name: ratelimitcli
Version: 0.1.1
Summary: A CLI to manage rate limits.
Home-page: https://docs.ratelimit.xyz
License: Apache-2.0
Author: Anwar
Author-email: anwar@anwarthink.com
Requires-Python: >=3.9,<4.0
Classifier: Development Status :: 2 - Pre-Alpha
Classifier: Intended Audience :: Developers
Classifier: License :: OSI Approved :: Apache Software License
Classifier: Operating System :: OS Independent
Classifier: Programming Language :: Python :: 3
Classifier: Programming Language :: Python :: 3 :: Only
Classifier: Programming Language :: Python :: 3.10
Classifier: Programming Language :: Python :: 3.9
Classifier: Topic :: Software Development :: Libraries :: Python Modules
Requires-Dist: aiohttp (>=3.8.1,<4.0.0)
Requires-Dist: python-jose (>=3.3.0,<4.0.0)
Requires-Dist: pytomlpp (>=1.0.11,<2.0.0)
Requires-Dist: requests (>=2.28.1,<3.0.0)
Requires-Dist: thriftpy2 (>=0.4.14,<0.5.0)
Requires-Dist: typer[all] (>=0.5.0,<0.6.0)
Project-URL: Documentation, https://docs.ratelimit.xyz
